explorecourses/__init__.py
explorecourses/classes.py
explorecourses/course_connection.py
explorecourses/filters.py
tests/__init__.py
tests/test_attribute.py
tests/test_course.py
tests/test_course_connection.py
tests/test_department.py
tests/test_instructor.py
tests/test_learning_objective.py
tests/test_schedule.py
tests/test_school.py
tests/test_section.py
tests/test_tag.py
explorecourses-1.0.6.dist-info/LICENSE
explorecourses-1.0.6.dist-info/METADATA
explorecourses-1.0.6.dist-info/WHEEL
explorecourses-1.0.6.dist-info/top_level.txt
explorecourses-1.0.6.dist-info/RECORD
