Metadata-Version: 2.1
Name: explorecourses
Version: 1.0.6
Summary: A Python API for Stanford Explore Courses
Home-page: https://github.com/illiteratecoder/Explore-Courses-API
Author: Jeremy Ephron
Author-email: jeremye@stanford.edu
License: UNKNOWN
Platform: UNKNOWN
Classifier: Programming Language :: Python
Classifier: Programming Language :: Python :: 3
Classifier: Programming Language :: Python :: 3.6
Classifier: License :: OSI Approved :: MIT License
Classifier: Operating System :: OS Independent
Requires-Dist: requests (>=2)
